{"data":[{"id":"6","gold_name":"\u0630\u0647\u0628 \u0639\u064a\u0627\u0631 21 \u063a\u0631\u0627\u0645","gold_value":"830000","gold_history":"818000","gold_history_status":"u","gold_history_def":12000},{"id":"7","gold_name":"\u0630\u0647\u0628 \u0639\u064a\u0627\u0631 22 \u063a\u0631\u0627\u0645","gold_value":"925000","gold_history":"912000","gold_history_status":"u","gold_history_def":13000},{"id":"8","gold_name":"\u0630\u0647\u0628 \u0639\u064a\u0627\u0631 18 \u063a\u0631\u0627\u0645","gold_value":"711429","gold_history":"701143","gold_history_status":"u","gold_history_def":10286},{"id":"9","gold_name":"\u0627\u0648\u0646\u0635\u0629 \u0639\u064a\u0627\u0631 24 \u063a\u0631\u0627\u0645","gold_value":"31055000","gold_history":"30600000","gold_history_status":"u","gold_history_def":455000},{"id":"10","gold_name":"\u0644\u064a\u0631\u0629 \u0639\u064a\u0627\u0631 21 \u063a\u0631\u0627\u0645","gold_value":"7050000","gold_history":"6925000","gold_history_status":"u","gold_history_def":125000}]}