{"data":[{"id":"6","gold_name":"\u0630\u0647\u0628 \u0639\u064a\u0627\u0631 21 \u063a\u0631\u0627\u0645","gold_value":"167000","gold_history":"166000","gold_history_status":"u","gold_history_def":1000},{"id":"7","gold_name":"\u0630\u0647\u0628 \u0639\u064a\u0627\u0631 22 \u063a\u0631\u0627\u0645","gold_value":"172000","gold_history":"171000","gold_history_status":"u","gold_history_def":1000},{"id":"8","gold_name":"\u0630\u0647\u0628 \u0639\u064a\u0627\u0631 18 \u063a\u0631\u0627\u0645","gold_value":"143143","gold_history":"142286","gold_history_status":"u","gold_history_def":857},{"id":"9","gold_name":"\u0627\u0648\u0646\u0635\u0629 \u0639\u064a\u0627\u0631 24 \u063a\u0631\u0627\u0645","gold_value":"5900114","gold_history":"6042286","gold_history_status":"d","gold_history_def":142172},{"id":"10","gold_name":"\u0644\u064a\u0631\u0629 \u0639\u064a\u0627\u0631 21 \u063a\u0631\u0627\u0645","gold_value":"1328000","gold_history":"1360000","gold_history_status":"d","gold_history_def":32000}]}